anb_python_components/__init__.py
anb_python_components/classes/__init__.py
anb_python_components/classes/action_state.py
anb_python_components/classes/dataclass_analyzer.py
anb_python_components/classes/directory.py
anb_python_components/classes/file.py
anb_python_components/classes/interface.py
anb_python_components/classes/shortcode_parser.py
anb_python_components/custom_types/__init__.py
anb_python_components/custom_types/guid.py
anb_python_components/custom_types/object_array.py
anb_python_components/custom_types/shortcode_attributes.py
anb_python_components/custom_types/two_dim_size.py
anb_python_components/custom_types/version_info.py
anb_python_components/decorators/__init__.py
anb_python_components/decorators/interface_decorators.py
anb_python_components/enums/__init__.py
anb_python_components/enums/message_type.py
anb_python_components/enums/not_bool_action.py
anb_python_components/enums/type_copy_strategy.py
anb_python_components/exceptions/__init__.py
anb_python_components/exceptions/wrong_type_exception.py
anb_python_components/extensions/__init__.py
anb_python_components/extensions/array_extension.py
anb_python_components/extensions/bool_extension.py
anb_python_components/extensions/dataclass_extension.py
anb_python_components/extensions/string_extension.py
anb_python_components/extensions/string_extension_constant.py
anb_python_components/extensions/type_extension.py
anb_python_components/models/__init__.py
anb_python_components/models/action_state_message.py
anb_python_components/models/shortcode_model.py
anb_python_components-1.4.3.dist-info/licenses/LICENSE
tests/__init__.py
tests/classes/__init__.py
tests/classes/action_state_test.py
tests/classes/dataclass_analyzer_test.py
tests/classes/directory_test.py
tests/classes/file_test.py
tests/classes/interface_test.py
tests/classes/shortcode_parser_test.py
tests/custom_types/__init__.py
tests/custom_types/guid_test.py
tests/custom_types/object_array_test.py
tests/custom_types/two_dim_size_test.py
tests/custom_types/version_info_test.py
anb_python_components-1.4.3.dist-info/METADATA
anb_python_components-1.4.3.dist-info/WHEEL
anb_python_components-1.4.3.dist-info/top_level.txt
anb_python_components-1.4.3.dist-info/RECORD
