Metadata-Version: 2.4
Name: anb_python_components
Version: 1.4.3
Summary: Набор компонентов Python, которые упрощают разработку / A set of Python components that simplify development
Home-page: https://gitflic.ru/project/babaev-an/anb-python-components
Author: Александр Бабаев
Author-email: contact_with_us@babaev-an.ru
Project-URL: Documentation, https://gitflic.ru/project/babaev-an/anb-python-components/wiki
Project-URL: Source, https://gitflic.ru/project/babaev-an/anb-python-components
Project-URL: Tracker, https://gitflic.ru/project/babaev-an/anb-python-components/issue?page=0
Keywords: python components development utils
Classifier: Development Status :: 5 - Production/Stable
Classifier: Intended Audience :: Developers
Classifier: License :: OSI Approved :: MIT License
Classifier: Programming Language :: Python :: 3.14
Classifier: Operating System :: OS Independent
Classifier: Topic :: Software Development :: Libraries :: Python Modules
Requires-Python: >=3.14.0
License-File: LICENSE
Requires-Dist: setuptools>=80.9.0
Dynamic: author
Dynamic: author-email
Dynamic: classifier
Dynamic: description
Dynamic: description-content-type
Dynamic: home-page
Dynamic: keywords
Dynamic: license-file
Dynamic: project-url
Dynamic: requires-dist
Dynamic: requires-python
Dynamic: summary
